{
  "99713963": {
    "name": "Няня (ул. 1905г)",
    "payment_to": 130000,
    "payment_from": 120000,
    "town": "Москва",
    "requirement": "Опыт работы в семьях. Рекомендации."
  },
  "99794264": {
    "name": "Няня (Бауманская)",
    "payment_to": 150000,
    "payment_from": 110000,
    "town": "Москва",
    "requirement": "Опыт работы обязателен. Рекомендации. Актуальные мед.анализы."
  },
  "99876006": {
    "name": "Няня",
    "payment_to": null,
    "payment_from": 168000,
    "town": "Москва",
    "requirement": "В прекрасную семью требуется няня для двух активных мальчиков 6 лет и 4 года. Мальчики посещают детский сад, ходят на..."
  },
  "99931783": {
    "name": "Редактор-корректор қазақ тілінде",
    "payment_to": 0,
    "payment_from": 0,
    "town": "Астана",
    "requirement": null
  },
  "97912491": {
    "name": "Няня в семью",
    "payment_to": 2000,
    "payment_from": 1000,
    "town": "Минск",
    "requirement": "с опытом работы на схожей работе или с опытом работы с детьми. - любовь к деткам (ищем человека, который понравится душой..."
  },
  "99231573": {
    "name": "Няня на дому",
    "payment_to": 220000,
    "payment_from": 180000,
    "town": "Алматы",
    "requirement": "Медицинская справка 075 (флюра+нарко/псих диспансер обязательно). Адресная справка. Личные качества - чистоплотная, порядочная, ответственная. Опыт работы с чужими детьми аналогичных..."
  }
}